litepolis/__init__.py
litepolis/core.py
litepolis/utils.py
litepolis-1.0.4.dist-info/licenses/LICENSE
litepolis-1.0.4.dist-info/METADATA
litepolis-1.0.4.dist-info/WHEEL
litepolis-1.0.4.dist-info/entry_points.txt
litepolis-1.0.4.dist-info/top_level.txt
litepolis-1.0.4.dist-info/RECORD
