Metadata-Version: 2.4
Name: litepolis
Version: 1.0.4
Summary: The package manager of a Customizable e-democracy opinion collection and insight mining system.
Author-email: Yuan XU <dev.source@outlook.com>
License: file: LICENSE
Project-URL: Homepage, https://github.com/NewJerseyStyle/LitePolis
License-File: LICENSE
Requires-Dist: fastapi
Requires-Dist: ray[serve]
Requires-Dist: GitPython
Requires-Dist: click
Provides-Extra: demo
Requires-Dist: litepolis-router-database; extra == "demo"
Requires-Dist: litepolis-router-example; extra == "demo"
Requires-Dist: litepolis-middleware-example; extra == "demo"
Requires-Dist: litepolis-ui-example; extra == "demo"
Dynamic: license-file
